autounrar/__init__.py
autounrar/autounrar.py
autounrar-0.1.0.dist-info/LICENSE
autounrar-0.1.0.dist-info/METADATA
autounrar-0.1.0.dist-info/WHEEL
autounrar-0.1.0.dist-info/top_level.txt
autounrar-0.1.0.dist-info/RECORD
