Metadata-Version: 2.2
Name: autounrar
Version: 0.1.0
Summary: A Python library designed to simplify handling RAR archives
Home-page: https://github.com/Jeffrey131313/unrar
Author: Jeffrey131313
Author-email: Jeffrey131313@creepermc.top
Classifier: Programming Language :: Python :: 3
Classifier: License :: OSI Approved :: MIT License
Classifier: Operating System :: OS Independent
Requires-Python: >=3.6
License-File: LICENSE
